crx_settings_override/__init__.py
crx_settings_override/apps.py
crx_settings_override/context_processors.py
crx_settings_override/models.py
crx_settings_override/tests.py
crx_settings_override/migrations/0001_initial.py
crx_settings_override/migrations/0002_alter_layoutsettingsoverride_options_and_more.py
crx_settings_override/migrations/0003_remove_layoutsettingsoverride_navbar_class_and_more.py
crx_settings_override/migrations/0004_alter_translatablenavbar_options.py
crx_settings_override/migrations/0005_alter_translatablefooter_options.py
crx_settings_override/migrations/__init__.py
crx_settings_override-1.0.0b0.dist-info/LICENSE
crx_settings_override-1.0.0b0.dist-info/METADATA
crx_settings_override-1.0.0b0.dist-info/WHEEL
crx_settings_override-1.0.0b0.dist-info/top_level.txt
crx_settings_override-1.0.0b0.dist-info/RECORD
