Metadata-Version: 2.1
Name: crx-settings-override
Version: 1.0.0b0
Summary: Overrides of default Wagtail CRX settings, eg. navbars, footers, etc.
Author-email: "LESPROJEKT-SLUŽBY Ltd." <h4e@lesprojekt.cz>
Project-URL: Homepage, https://github.com/hslayers/crx-hslayers
Project-URL: Bug Tracker, https://github.com/hslayers/crx-hslayers/issues
Classifier: Programming Language :: Python :: 3
Classifier: Intended Audience :: Developers
Classifier: Operating System :: OS Independent
Requires-Python: >=3.7
License-File: LICENSE
Requires-Dist: coderedcms >=2.0.0
Requires-Dist: pynpm >=0.1.2
